code/__init__.py
code/csv_intersection.py
csv_intersection/__init__.py
csv_intersection/csv_intersection.py
csv_intersection-1.0.4.dist-info/LICENSE
csv_intersection-1.0.4.dist-info/METADATA
csv_intersection-1.0.4.dist-info/WHEEL
csv_intersection-1.0.4.dist-info/top_level.txt
csv_intersection-1.0.4.dist-info/RECORD
