Metadata-Version: 2.1
Name: csv-intersection
Version: 1.0.4
Summary: CSV intersection
Home-page: https://github.com/swapnalshahil/csv_intersection
Author: Swapnal Shahil
Author-email: swapnalsahil@gmail.com
License: MIT
Project-URL: Bug Reports, https://github.com/swapnalshahil/csv_intersection/issues
Project-URL: Source, https://github.com/swapnalshahil/csv_intersection
Keywords: csv,intersection,csv_intersection,tsv,tsv_intersection,common data,data visualization
Platform: UNKNOWN
Classifier: Programming Language :: Python :: 3.6
Classifier: License :: OSI Approved :: MIT License
Classifier: Operating System :: OS Independent
Requires-Python: >=3.6
License-File: LICENSE
Requires-Dist: python-csv
